splitscreen_mcp/__init__.py
splitscreen_mcp/__main__.py
splitscreen_mcp/logging_utils.py
splitscreen_mcp/window_actions.py
mcpcn_splitscreen-0.1.23.dist-info/METADATA
mcpcn_splitscreen-0.1.23.dist-info/WHEEL
mcpcn_splitscreen-0.1.23.dist-info/entry_points.txt
mcpcn_splitscreen-0.1.23.dist-info/licenses/LICENSE
mcpcn_splitscreen-0.1.23.dist-info/RECORD
