Metadata-Version: 2.4
Name: mcpcn-splitscreen
Version: 0.1.23
Summary: Model Context Protocol Server via Cross-Platform (Mac & Windows) Split Screen Functions
Project-URL: Homepage, https://github.com/Beta0415/computer-split-screen-mcp
Project-URL: Repository, https://github.com/Beta0415/computer-split-screen-mcp
Project-URL: Documentation, https://github.com/Beta0415/computer-split-screen-mcp#readme
Project-URL: Issues, https://github.com/Beta0415/computer-split-screen-mcp/issues
Author: Beta
License: MIT License
License-File: LICENSE
Keywords: cross-platform,desktop-productivity,macos,mcp,pywin32,split-screen,tiling,window-management,windows
Requires-Python: >=3.10
Requires-Dist: mcp>=0.1.0
Requires-Dist: pyobjc-core<12,>=10.1; sys_platform == 'darwin'
Requires-Dist: pyobjc-framework-applicationservices<12,>=10.1; sys_platform == 'darwin'
Requires-Dist: pyobjc-framework-cocoa<12,>=10.1; sys_platform == 'darwin'
Requires-Dist: pyobjc-framework-quartz<12,>=10.1; sys_platform == 'darwin'
Requires-Dist: pywin32>=306; sys_platform == 'win32'
